pyhunt/__init__.py
pyhunt/cli.py
pyhunt/colors.py
pyhunt/config.py
pyhunt/console.py
pyhunt/context.py
pyhunt/decorator.py
pyhunt/helpers.py
pyhunt/logger.py
pyhunt/utils.py
pyhunt-1.2.0.dist-info/METADATA
pyhunt-1.2.0.dist-info/WHEEL
pyhunt-1.2.0.dist-info/entry_points.txt
pyhunt-1.2.0.dist-info/licenses/LICENSE
pyhunt-1.2.0.dist-info/RECORD
