Metadata-Version: 2.4
Name: pyhunt
Version: 1.2.0
Summary: Lightweight Python logging tool for visual call tracing, tree-structured colored logs, and easy debugging with a simple decorator. Optimized for both standard and AI-generated codebases. 
Project-URL: source, https://github.com/easydevv/pyhunt
Author-email: EasyDev <easydevv@gmail.com>
License-File: LICENSE
Classifier: License :: OSI Approved :: MIT License
Classifier: Operating System :: OS Independent
Classifier: Programming Language :: Python :: 3.12
Requires-Python: >=3.12
Requires-Dist: dotenv>=0.9.9
